{
  "DSCN0415_001.jpeg": {
    "location": "The Embarcadero, North Beach, San Francisco, California, 94113, United States",
    "latitude": 37.80731111111111,
    "longitude": -122.4039638888889,
    "dateTaken": "2013-11-22T14:45:20.000Z"
  },
  "DSCN0416_002.jpeg": {
    "location": "The Embarcadero, North Beach, San Francisco, California, 94113, United States",
    "latitude": 37.807063888888884,
    "longitude": -122.40382777777778,
    "dateTaken": "2013-11-22T14:45:44.000Z"
  },
  "DSCN0419_003.jpeg": {
    "location": "The Embarcadero, Telegraph Hill, North Beach, San Francisco, California, 94113, United States",
    "latitude": 37.80847222222222,
    "longitude": -122.40299722222223,
    "dateTaken": "2013-11-22T14:47:11.000Z"
  },
  "DSCN0420_004.jpeg": {
    "location": "The Embarcadero, North Beach, San Francisco, California, 94113, United States",
    "latitude": 37.808836111111106,
    "longitude": -122.40250833333334,
    "dateTaken": "2013-11-22T14:47:32.000Z"
  }
}